s3labeler/__init__.py
s3labeler/__main__.py
s3labeler/s3labeler.py
s3labeler-1.0.5.dist-info/LICENSE
s3labeler-1.0.5.dist-info/METADATA
s3labeler-1.0.5.dist-info/WHEEL
s3labeler-1.0.5.dist-info/entry_points.txt
s3labeler-1.0.5.dist-info/top_level.txt
s3labeler-1.0.5.dist-info/RECORD
